cross/design.v
module crossbar
  
  #(
    parameter WIDTH = 8
  )

  (input              clk,
   input              rst_n,
   
   input              s0_val,
   input            s0_dst, 
   input      [WIDTH-1:0]   s0_data, 
   output reg         s0_rdy, 
   
   input            s1_val,  
   input            s1_dst,  
   input      [WIDTH-1:0]   s1_data, 
   output reg         s1_rdy,
   
   output reg         m0_val,
   output reg         m0_src, 
   output reg [WIDTH-1:0]   m0_data,
   input            m0_rdy,
   
   output reg         m1_val,
   output reg         m1_src, 
   output reg [WIDTH-1:0]   m1_data,
   input            m1_rdy);

  always @(clk or negedge rst_n) begin
    
 //---------------------------------------------------------reset  
    if (rst_n == 1'b0) begin
      m0_val <= 0; // tells enviroment that data is a lie
      m1_val <= 0;
      s0_rdy <= 0; // not ready to get any data ..
      s1_rdy <= 0; 
    end 
 //---------------------------------------------------------------
      
    if (clk == 1) begin
      
 //-----------------------------------------------check regs & dst    
   
     if ((s0_dst == 0 && m0_val == 1) || (s0_dst == 1 && m1_val == 1)) 
     begin
      s0_rdy <= 0;
     end 
      
     if ((s1_dst == 0 && m0_val == 1) || (s1_dst == 1 && m1_val == 1)) 
     begin
      s1_rdy <= 0;  
     end 
 
//---------------------------------------------------------------
  

      
//-------------------------------if everything is ok - get message 
      
      if ((s0_dst == 0 && m0_val == 0) || (s0_dst == 1 && m1_val == 0)) 
      begin
        s0_rdy <= 1;
      end
      
      if ((s1_dst == 0 && m0_val == 0) || (s1_dst == 1 && m1_val == 0)) 
      begin
        s1_rdy <= 1;  
      end  
      
      if (s0_rdy && s0_val) begin             // if input data is valid         
    if ((s0_dst == 0) && (m0_rdy==1)) begin // check destination, check if env is ready
          m0_data <= s0_data;
            m0_val  <= 1;
            m0_src  <= 0;
        end 
        
        if ((s0_dst == 1) && (m1_rdy==1)) begin
            m1_data <= s0_data;
            m1_val  <= 1;
            m1_src  <= 0;
        end
      end 

      if (s1_rdy && s1_val) begin
        if ((s1_dst == 0) && ((s1_dst!=s0_dst) || (s0_val==0)) 
                && (m0_rdy==1)) begin // +priority check +s0 valid check          
            m0_data <= s1_data;
            m0_val  <= 1;
            m0_src  <= 1;
        end     
    
          if ((s1_dst == 1) && (s1_dst!=s0_dst || (s0_val==0))
                  && (m1_rdy==1)) begin         
            m1_data <= s1_data;
            m1_val  <= 1;
            m1_src  <= 1; 
        end        
       end  
      
    end 
    
    if (clk == 0 && m0_rdy) begin
      m0_val <=0; 
    end
    if (clk == 0 && m1_rdy) begin
      m1_val <=0; 
    end
    
end
endmodule

cross/test.v
 `timescale 10ns / 10ns

module test;
  parameter WIDTH = 8;
  
  reg 				clk;
  reg 				rst_n;
  reg 				s0_val;
  reg 				s0_dst;
  reg  [WIDTH-1:0]  s0_data;
  wire 				s0_rdy;
  reg 				s1_val; 
  reg 				s1_dst;
  reg  [WIDTH-1:0]  s1_data;
  wire 				s1_rdy;
  wire 				m0_val;
  wire 				m0_src;
  wire [WIDTH-1:0]  m0_data;
  reg 				m0_rdy;
  wire 				m1_val;
  wire 				m1_src;
  wire [WIDTH-1:0]  m1_data;
  reg 				m1_rdy;
  
  crossbar 
  #(.WIDTH(WIDTH))
  CROSSBAR (.clk(clk), 
            .rst_n(rst_n),      
            .s0_val(s0_val),
            .s0_dst(s0_dst),
            .s0_data(s0_data),
            .s0_rdy(s0_rdy),
            .s1_val(s1_val),
            .s1_dst(s1_dst), 
            .s1_data(s1_data),
  			.s1_rdy(s1_rdy),
            .m0_val(m0_val),
  			.m0_src(m0_src),
  			.m0_data(m0_data), 
  			.m0_rdy(m0_rdy),
            .m1_val(m1_val),
  			.m1_src(m1_src), 
  			.m1_data(m1_data),
            .m1_rdy(m1_rdy));            
  
    initial begin
    	$dumpfile("dump.vcd");
    	$dumpvars(1);
    	clk = 1'b0;
      	assert (clk == 1'b0) $display ("clock = 0");
    	forever #5 clk = ~clk;
    end
  
 
  	initial begin
    	rst_n    = 1;  
		#1 rst_n = 0;
        assert (rst_n == 0) $display ("rst_n = 0");
   		#3 rst_n = 1; 
      	assert (rst_n == 1) $display ("rst_n = 1");
 //----------------------------------------------------
    	s0_data <= 1;//data
   		s0_dst   = 0; // 0 for m0, 1 for m1
    	s0_val  <= 1;  // 1 is ok
    
    	s1_data <= 2;// same settings 
    	s1_dst   = 1; 
    	s1_val  <= 1; 
     	assert (s0_dst == 0 && s1_dst == 1) 
        	$display ("s0->m0 s1->m1");
    	m0_rdy  <= 1;
      
    	m1_rdy  <= 1;
 //----------------------------------------------------
		#1 rst_n = 0;
		m0_rdy = 0;
		m1_rdy = 0;
   		#2 rst_n = 1;
		assert (m0_rdy == 0 && m1_rdy == 0) 
        	$display ("reset with m(0)_rdy, m(1)_rdy = 0");
//----------------------------------------------------
    #10 
    	s0_data <= 3;//data
    	s0_dst   = 0; // 0 for m0, 1 for m1
    	s0_val  <= 1;  // 1 is ok
    
    	s1_data <= 4;// same settings 
    	s1_dst   = 1; 
    	s1_val  <= 1;
      
    	m0_rdy  = 1;
      
    	m1_rdy  = 0; 
        assert (m0_rdy == 1 && m1_rdy == 0) 
          $display ("s0->m0 s1->m1, m1_rdy = 0");
 //----------------------------------------------------
    #10 
    	s0_data <= 1;//data
    	s0_dst   = 1; // 0 for m0, 1 for m1
    	s0_val  <= 1;  // 1 is ok
    
    	s1_data <= 2;// same settings 
    	s1_dst   = 0; 
    	s1_val  <= 1; 
      
     	assert (s0_dst == 1 && s1_dst == 0) 
        	$display ("s0->m1 s1->m0");
      
    	m0_rdy  <= 1;
      
    	m1_rdy  <= 1;
 //----------------------------------------------------
    #10 
    	s0_data <= 3;//data
    	s0_dst   = 0; // 0 for m0, 1 for m1
    	s0_val  <= 1;  // 1 is ok
    
    	s1_data <= 4;// same settings 
    	s1_dst   = 0; 
    	s1_val  <= 1; 
      
      	assert (s0_dst == 0 && s1_dst == 0) 
        	$display ("s0->m0 s1->m0, prioity check");
      
    	m0_rdy  <= 1;
      
    	m1_rdy  <= 1;  
 //----------------------------------------------------
    #10 
    	s0_data <= 1;//data
    	s0_dst   = 0; // 0 for m0, 1 for m1
    	s0_val   = 0;  // 1 is ok
    
    	s1_data <= 2;// same settings 
    	s1_dst   = 0; 
    	s1_val  <= 1; 
      
      	assert (s0_dst == 0 && s1_dst == 0 && s0_val==0) 
        	$display ("s0->m0 s1->m0, s0 isn't valid");
      
      	m0_rdy  <= 1;
      
    	m1_rdy  <= 1;
 //----------------------------------------------------
    #10 
    	s0_data <= 5;//data
    	s0_dst   = 1; // 0 for m0, 1 for m1
    	s0_val  <= 1;  // 1 is ok
    
    	s1_data <= 6;// same settings 
    	s1_dst   = 1; 
    	s1_val   = 0; 
      
      	assert (s0_dst == 1 && s1_dst == 1 && s1_val==0) 
        	$display ("s0->m1 s1->m1, s1 isn't valid");
     
    	m0_rdy  <= 1;
      
    	m1_rdy  <= 1;
 //----------------------------------------------------
    #10 
    	s0_data <= 5;//data
    	s0_dst  <= 0; // 0 for m0, 1 for m1
    	s0_val  <= 1;  // 1 is ok
    
    	s1_data <= 6;// same settings 
    	s1_dst  <= 1; 
    	s1_val  <= 1; 
     
    	m0_rdy   = 0;
      
    	m1_rdy  <= 1;
      	
      	assert (m0_rdy == 0) 
        	$display ("s0->m0 s1->m1, m0 isn't ready");
 //----------------------------------------------------
    #10 
    	s0_data <= 7;//data
    	s0_dst  <= 0; // 0 for m0, 1 for m1
    	s0_val  <= 1;  // 1 is ok
    
    	s1_data <= 6;// same settings 
    	s1_dst  <= 1; 
    	s1_val  <= 1; 
     
    	m0_rdy  <= 1;
      
    	m1_rdy   = 0;  
      
     	assert (m1_rdy == 0) 
       		$display ("s0->m0 s1->m1, m1 isn't ready");
 //----------------------------------------------------
  #10 $finish;
  end 
  
endmodule

cross/dump.vcd
$date
	Tue Nov 14 20:51:32 2017
$end
$version
	Icarus Verilog
$end
$timescale
	10ns
$end
$scope module test $end
$var wire 1 ! s1_rdy $end
$var wire 1 " s0_rdy $end
$var wire 1 # m1_val $end
$var wire 1 $ m1_src $end
$var wire 8 % m1_data [7:0] $end
$var wire 1 & m0_val $end
$var wire 1 ' m0_src $end
$var wire 8 ( m0_data [7:0] $end
$var reg 1 ) clk $end
$var reg 1 * m0_rdy $end
$var reg 1 + m1_rdy $end
$var reg 1 , rst_n $end
$var reg 8 - s0_data [7:0] $end
$var reg 1 . s0_dst $end
$var reg 1 / s0_val $end
$var reg 8 0 s1_data [7:0] $end
$var reg 1 1 s1_dst $end
$var reg 1 2 s1_val $end
$upscope $end
$enddefinitions $end
#0
$dumpvars
x2
x1
bx 0
x/
x.
bx -
1,
x+
x*
0)
bx (
x'
x&
bx %
x$
x#
x"
x!
$end
#1
0!
0"
0#
0&
0,
#4
1+
1*
12
b10 0
1/
b1 -
11
0.
1,
#5
0+
0*
0,
1)
#7
1,
#10
0)
#15
1)
#17
1*
b100 0
b11 -
#20
0)
#25
0'
1&
b11 (
1"
1)
#27
1+
b10 0
b1 -
01
1.
#30
0)
#35
1'
b10 (
0$
1#
b1 %
1!
1)
#37
b100 0
b11 -
0.
#40
0)
#45
0'
b11 (
1)
#47
b10 0
b1 -
0/
#50
0)
#55
1'
b10 (
1)
#57
b110 0
1/
b101 -
02
11
1.
#60
0)
#65
b101 %
1)
#67
12
0.
0*
#70
0)
#75
1$
b110 %
0&
1)
#77
1*
b111 -
0+
#80
0)
#85
0'
1&
b111 (
0#
1)
