Bus_upsizer/BusUpsizer.v
module BusUpsizer
#(   
	parameter S_DATA_WIDTH = 8
	,M_DATA_WIDTH = 32
)
(
	 input wire clock
	,input wire reset
	,input wire s_val
	,input wire [S_DATA_WIDTH-1:0] s_data
	,input wire m_rdy
	,output reg s_rdy
	,output reg m_val	
	,output reg [M_DATA_WIDTH-1:0] m_data
);
  
reg [1:0] counter;
reg [S_DATA_WIDTH-1:0] m_data1, m_data2, m_data3, m_data4;

always @(posedge clock or posedge reset)
  begin
	  	if (reset) 
	  	begin
	  	 	counter <= 1'b0;
	  	 	m_val <= 0; 
		  	s_rdy <= 0;	
		  
	    end 
		else 
		begin
		    if (s_rdy == 1'b1 && s_val == 1'b1) 
			begin
			  	counter <= counter + 1'b1;
				case(counter)
					2'b00: m_data1 <= s_data;
					2'b01: m_data2 <= s_data;
					2'b10: m_data3 <= s_data;
					2'b11: m_data4 <= s_data;
				endcase	
			end
	  	end

		if (counter == 2'b11) 
		begin
		    m_val <= 1;
		    m_rdy <= 1;
		end
		    else begin
		        m_val <=0;
		        s_rdy <=0;
		    end
		m_data <= {m_data1, m_data2, m_data3, m_data4};	
	end
endmodule

Bus_upsizer/BusUpsizerTest.v
`timescale 10ns / 10ns

module BusUpsizerTest;
  parameter S_DATA_WIDTH = 8, M_DATA_WIDTH = 32;
  reg clock;
  reg reset;
  reg s_val;
  reg [S_DATA_WIDTH-1:0] s_data;
  reg m_rdy;
  wire s_rdy;
  wire m_val;
  wire [M_DATA_WIDTH-1:0] m_data;
 
  BusUpsizer #(.S_DATA_WIDTH(S_DATA_WIDTH), 
               .M_DATA_WIDTH(M_DATA_WIDTH))
  BUS

  (
    .clock(clock), 
    .reset(reset), 
    .s_val (s_val),
    .s_data(s_data), 
    .m_rdy (m_rdy),
    .s_rdy (s_rdy),
    .m_val (m_val),
    .m_data(m_data)
  );


initial begin
      $dumpfile("BusUpsizer.vcd");
      $dumpvars(0);
      clock = 1'b0;
      //assert (clk == 1'b0) $display ("clock = 0");
      forever #5 clock = ~clock;
    end
  
initial begin
    $dumpfile("BusUpsizer.vcd");
    $dumpvars(0,BUS);
    m_rdy = 0;
    s_val = 0;
    clock = 1;
    reset = 1;
    s_data = 8'b00000000; 
      repeat(1) #1 clock = ~clock;
      $display("Reset all");
      
    clock = 1;
    reset = 0;
    m_rdy=1;
    s_val = 1;
    s_data = 8'b00010000;
      repeat(8) #1  clock = ~clock;  
    
    clock = 1;
    reset = 0;
    m_rdy=1;
    s_val = 1;
    s_data =  8'b00000001;
      repeat(8) #1 clock = ~clock;
  clock = ~clock;
   
    
    clock = 1;
    reset = 0;
    m_rdy=1;
    s_val = 1;
    s_data =  8'b00000010;
    repeat(8) #1 clock = ~clock;
      
    clock = 1;
    reset = 0;
    m_rdy=1;
    s_val = 1;
    s_data =  8'b00000100;
    repeat(8) #1 clock = ~clock;
   
    $finish;
  end

endmodule

Bus_upsizer/BusUpsizer.vcd
$date
	Thu Nov 30 12:05:45 2017
$end
$version
	Icarus Verilog
$end
$timescale
	10ns
$end
$scope module BusUpsizerTest $end
$var wire 1 ! s_rdy $end
$var wire 1 " m_val $end
$var wire 32 # m_data [31:0] $end
$var reg 1 $ clock $end
$var reg 1 % m_rdy $end
$var reg 1 & reset $end
$var reg 8 ' s_data [7:0] $end
$var reg 1 ( s_val $end
$scope module BUS $end
$var wire 1 $ clock $end
$var wire 1 % m_rdy $end
$var wire 1 & reset $end
$var wire 8 ) s_data [7:0] $end
$var wire 1 ( s_val $end
$var reg 2 * counter [1:0] $end
$var reg 32 + m_data [31:0] $end
$var reg 8 , m_data1 [7:0] $end
$var reg 8 - m_data2 [7:0] $end
$var reg 8 . m_data3 [7:0] $end
$var reg 8 / m_data4 [7:0] $end
$var reg 1 " m_val $end
$var reg 1 ! s_rdy $end
$upscope $end
$upscope $end
$scope module BusUpsizerTest $end
$scope module BUS $end
$upscope $end
$upscope $end
$enddefinitions $end
#0
$dumpvars
bx /
bx .
bx -
bx ,
bx +
b0 *
b0 )
0(
b0 '
1&
0%
1$
bx #
0"
0!
$end
#1
b10000 ,
b1 *
b10000 '
b10000 )
1(
1%
0&
1$
#2
0$
#3
b10000xxxxxxxxxxxxxxxxxxxxxxxx #
b10000xxxxxxxxxxxxxxxxxxxxxxxx +
b10000 -
b10 *
1$
#4
0$
#5
b1000000010000xxxxxxxxxxxxxxxx #
b1000000010000xxxxxxxxxxxxxxxx +
b10000 .
b11 *
0$
#6
b100000001000000010000xxxxxxxx #
b100000001000000010000xxxxxxxx +
1!
1"
b10000 /
b0 *
1$
#7
0$
#8
b10000000100000001000000010000 #
b10000000100000001000000010000 +
0!
0"
b1 *
1$
#9
b1 -
b10 *
b1 '
b1 )
1$
#10
b10000000000010001000000010000 #
b10000000000010001000000010000 +
b1 .
b11 *
1$
#11
0$
#12
b10000000000010000000100010000 #
b10000000000010000000100010000 +
1!
1"
b1 /
b0 *
1$
#13
0$
#14
b10000000000010000000100000001 #
b10000000000010000000100000001 +
0!
0"
b1 ,
b1 *
1$
#15
b1000000010000000100000001 #
b1000000010000000100000001 +
b10 *
1$
#16
0$
#17
b10 .
b11 *
b10 '
b10 )
1$
#18
0$
#19
b1000000010000001000000001 #
b1000000010000001000000001 +
1!
1"
b10 /
b0 *
1$
#20
b1000000010000001000000010 #
b1000000010000001000000010 +
0!
0"
b10 ,
b1 *
1$
#21
0$
#22
b10000000010000001000000010 #
b10000000010000001000000010 +
b10 -
b10 *
1$
#23
0$
#24
b10000000100000001000000010 #
b10000000100000001000000010 +
b11 *
1$
#25
1!
1"
b100 /
b0 *
b100 '
b100 )
1$
#26
0$
#27
b10000000100000001000000100 #
b10000000100000001000000100 +
0!
0"
b100 ,
b1 *
1$
#28
0$
#29
b100000000100000001000000100 #
b100000000100000001000000100 +
b100 -
b10 *
1$
#30
b100000001000000001000000100 #
b100000001000000001000000100 +
b100 .
b11 *
1$
#31
0$
#32
b100000001000000010000000100 #
b100000001000000010000000100 +
1!
1"
b0 *
1$
