testbench/bench.v
module bench
  #( parameter DATA_WIDTH = 8
  ,  parameter ATTR_WIDTH = 4
  ,  parameter SIGN       = 0
  ,  parameter OVERFLOW   = 1
  )
  ( input  wire                  clk
  , input  wire                  signal_load
  , input  wire                  signal_init
  , input  wire                  signal_neg
  , input  wire [DATA_WIDTH-1:0] data_in
  , input  wire [ATTR_WIDTH-1:0] attr_in

  , input  wire                  signal_oe
  , output reg  [DATA_WIDTH-1:0] data_out
  , output reg  [ATTR_WIDTH-1:0] attr_out
  );


reg [DATA_WIDTH-1:0]   ext_arg;
reg [DATA_WIDTH-1:0]   int_arg;
reg [DATA_WIDTH:0]     acc; // +1 на переполнение
reg overflow;


always @(posedge clk)
  if ( signal_load ) begin
    if ( signal_init ) begin
   	  overflow <= attr_in[ OVERFLOW ];
      int_arg <= 0;
    end else begin 
      overflow = overflow || attr_in[ OVERFLOW ];
      int_arg = acc[DATA_WIDTH:0];
    end
    ext_arg = signal_neg ? -data_in : data_in;
  end


wire [DATA_WIDTH:0]  wacc; // +1 на переполнение
wire carry;

// https://en.wikipedia.org/wiki/Two%27s_complement#Addition
assign { carry, wacc[DATA_WIDTH-2:0] } = ext_arg[DATA_WIDTH-2:0] + int_arg[DATA_WIDTH-2:0];
assign wacc[DATA_WIDTH:DATA_WIDTH-1]   = ext_arg[DATA_WIDTH-1] + int_arg[DATA_WIDTH-1] + carry;

always @(posedge clk) begin
    acc[DATA_WIDTH:0] <= wacc;
    //overflow <= carry ^ acc[DATA_WIDTH];
  end


always @(posedge clk)
  if ( ~signal_oe )
    { attr_out, data_out } <= 0;
  else begin
    data_out           <= acc[DATA_WIDTH-1:0];
    attr_out[SIGN]     <= acc[DATA_WIDTH];
    attr_out[OVERFLOW] <= overflow;
  end             

endmodule

testbench/testbench_last.v
`timescale 1 ps/ 1 ps
module testbench_last
#(   parameter DATA_WIDTH = 8
  ,  parameter ATTR_WIDTH = 4
  ,  parameter SIGN       = 0
  ,  parameter OVERFLOW   = 1
)
(); 
reg clk 
,   signal_load
,   signal_init
,   signal_neg
,   signal_oe; 

localparam START = 1'b1;
localparam STOP  = 1'b0;

reg [DATA_WIDTH-1:0] data_in;
reg [ATTR_WIDTH-1:0] attr_in = 0;

wire [DATA_WIDTH-1:0] data_out;

bench unit_under_test (
    .clk(clk),
    .signal_load(signal_load),
    .signal_init(signal_init),
    .signal_neg(signal_neg),
    .signal_oe(signal_oe),
    .data_in(data_in),
    .attr_in(attr_in),
    .data_out(data_out)
);

task nop; // nop
    begin
        signal_load <= 0;
        signal_init <= 0;
        signal_neg  <= 0;
        signal_oe   <= 0;
        data_in     <= 0;
    end
endtask

task Initialization;
    input [DATA_WIDTH-1:0] id;
    begin
        signal_load <= 1;
        signal_init <= 1;
        signal_neg  <= 0;
        signal_oe   <= 0;
        data_in     <= id;
    end
endtask

task Load_Data;
    input [DATA_WIDTH-1:0] id;
    begin
        signal_load <= 1;
        signal_init <= 0;
        signal_neg  <= 0;
        signal_oe   <= 0;
        data_in     <= id;
    end
endtask

task outputdata;
    begin
        signal_load <= 0;
        signal_init <= 0;
        signal_neg  <= 0;
        signal_oe   <= 1;
    end
endtask


//task Initialization;
  //  input x_init;
    //begin
      //  signal_init <= x_init;
  //  end
//endtask

task Send_Value;
    input [DATA_WIDTH-1:0] data;
    begin
        data_in = data;
    end
endtask

task Send_Data_Out;
    input x_oe;
    begin
        signal_oe = x_oe;
    end
endtask

task Send_Neg;
    input x_neg;
    begin
        signal_neg = x_neg;
    end
endtask

always
  #5 clk = ~clk;
reg RST;

initial 
  begin
    RST <= 1;
    $display("Start programm");
    clk = 0;

    nop(); @(posedge clk);
 
//    Load_Data(START);                @(posedge clk);
    RST <= 0;
    Initialization (25);       @(posedge clk);
    nop(); @(posedge clk);
    Load_Data(25);                 @(posedge clk);
    // Initialization (STOP);           @(posedge clk);
    // Send_Value(3);         repeat(2) @(posedge clk);
    // Send_Neg(START);                 @(posedge clk);
    // Send_Value(2);                   @(posedge clk);    
    // Load_Data(STOP);                 @(posedge clk);
    // Send_Neg(STOP);                  @(posedge clk);
    // Send_Data_Out(START);            @(posedge clk);
    // Send_Data_Out(STOP);             @(posedge clk);

    nop(); repeat(10) @(posedge clk);
    outputdata(); repeat(10) @(posedge clk);

    Initialization (5);   repeat(2) @(posedge clk);
    Load_Data(5);                 @(posedge clk);
    nop(); repeat(10) @(posedge clk);
    outputdata(); repeat(10) @(posedge clk);

    // nop(); @(posedge clk);

    // Load_Data(START);                @(posedge clk);
    // Initialization (START);          @(posedge clk);
    // Initialization (STOP);           @(posedge clk);
    // Send_Value(5);         repeat(2) @(posedge clk);
    // Send_Data_Out(START);            @(posedge clk);
    // Send_Data_Out(STOP);             @(posedge clk);
    // Send_Value(1);         repeat(2) @(posedge clk);
    // Send_Value(data_out);            @(posedge clk);
    // Send_Data_Out(START);            @(posedge clk);
    // Load_Data(STOP);                @(posedge clk);
    // Send_Data_Out(STOP);             @(posedge clk);



  //Initialization(START); @(posedge clk);
  //Initialization(STOP);  //@(posedge clk);


  end

initial
begin
  #6000 $finish;
end

initial
begin
    $dumpfile("bench.vcd");
    $dumpvars(0, testbench_last);
    $display("finish");
end 

endmodule

// ----------------------------------------------
// iverilog -o test -I./ -y./ bench.v testbench.v
// vvp test
// gtkwave bench.vcd
// iverilog -o test -I./ -y./ bench.v testbench.v && vvp test && gtkwave bench.vcd
// ----------------------------------------------

testbench/bench.vcd
$date
	Fri Dec 22 13:45:37 2017
$end
$version
	Icarus Verilog
$end
$timescale
	1ps
$end
$scope module testbench_last $end
$var wire 8 ! data_out [7:0] $end
$var reg 1 " RST $end
$var reg 4 # attr_in [3:0] $end
$var reg 1 $ clk $end
$var reg 8 % data_in [7:0] $end
$var reg 1 & signal_init $end
$var reg 1 ' signal_load $end
$var reg 1 ( signal_neg $end
$var reg 1 ) signal_oe $end
$scope module unit_under_test $end
$var wire 4 * attr_in [3:0] $end
$var wire 1 $ clk $end
$var wire 8 + data_in [7:0] $end
$var wire 1 & signal_init $end
$var wire 1 ' signal_load $end
$var wire 1 ( signal_neg $end
$var wire 1 ) signal_oe $end
$var wire 9 , wacc [8:0] $end
$var wire 1 - carry $end
$var reg 9 . acc [8:0] $end
$var reg 4 / attr_out [3:0] $end
$var reg 8 0 data_out [7:0] $end
$var reg 8 1 ext_arg [7:0] $end
$var reg 8 2 int_arg [7:0] $end
$var reg 1 3 overflow $end
$upscope $end
$scope task Initialization $end
$var reg 8 4 id [7:0] $end
$upscope $end
$scope task Load_Data $end
$var reg 8 5 id [7:0] $end
$upscope $end
$scope task Send_Data_Out $end
$var reg 1 6 x_oe $end
$upscope $end
$scope task Send_Neg $end
$var reg 1 7 x_neg $end
$upscope $end
$scope task Send_Value $end
$var reg 8 8 data [7:0] $end
$upscope $end
$scope task nop $end
$upscope $end
$scope task outputdata $end
$upscope $end
$upscope $end
$enddefinitions $end
#0
$dumpvars
bx 8
x7
x6
bx 5
bx 4
x3
bx 2
bx 1
bx 0
bx /
bx .
x-
bx ,
b0 +
b0 *
0)
0(
0'
0&
b0 %
0$
b0 #
1"
bx !
$end
#5
b11001 %
b11001 +
1&
1'
b0 /
b0 !
b0 0
0"
b11001 4
1$
#10
0$
#15
b11001 ,
0-
b0 %
b0 +
0&
0'
b0 2
03
b11001 1
1$
#20
0$
#25
b11001 %
b11001 +
1'
b11001 .
b11001 5
1$
#30
0$
#35
b0 %
b0 +
0'
b110010 ,
b11001 2
1$
#40
0$
#45
b110010 .
1$
#50
0$
#55
1$
#60
0$
#65
1$
#70
0$
#75
1$
#80
0$
#85
1$
#90
0$
#95
1$
#100
0$
#105
1$
#110
0$
#115
1$
#120
0$
#125
1$
#130
0$
#135
1)
1$
#140
0$
#145
b110010 !
b110010 0
1$
#150
0$
#155
1$
#160
0$
#165
1$
#170
0$
#175
1$
#180
0$
#185
1$
#190
0$
#195
1$
#200
0$
#205
1$
#210
0$
#215
1$
#220
0$
#225
1$
#230
0$
#235
b101 %
b101 +
0)
1&
1'
b101 4
1$
#240
0$
#245
b0 2
b0 !
b0 0
b101 ,
b101 1
1$
#250
0$
#255
0&
b101 .
b101 5
1$
#260
0$
#265
b0 %
b0 +
0'
b1010 ,
b101 2
1$
#270
0$
#275
b1010 .
1$
#280
0$
#285
1$
#290
0$
#295
1$
#300
0$
#305
1$
#310
0$
#315
1$
#320
0$
#325
1$
#330
0$
#335
1$
#340
0$
#345
1$
#350
0$
#355
1$
#360
0$
#365
1)
1$
#370
0$
#375
b1010 !
b1010 0
1$
